easysurfvis/__init__.py
easysurfvis/profile_analysis.py
easysurfvis/query_server.py
easysurfvis/surface_visualization.py
easysurfvis/cores/__init__.py
easysurfvis/cores/afni_extension.py
easysurfvis/cores/custom_matplotlib.py
easysurfvis/cores/general_util.py
easysurfvis/cores/surface_data.py
easysurfvis/cores/surface_roi.py
easysurfvis/cores/surface_util.py
easysurfvis/data/ROI/Brodmann/L_roi_values.npy
easysurfvis/data/ROI/Brodmann/L_roi_vertex_info.json
easysurfvis/data/ROI/Brodmann/L_rois.npy
easysurfvis/data/ROI/Brodmann/R_roi_values.npy
easysurfvis/data/ROI/Brodmann/R_roi_vertex_info.json
easysurfvis/data/ROI/Brodmann/R_rois.npy
easysurfvis/data/ROI/FAN/L_roi_values.npy
easysurfvis/data/ROI/FAN/L_roi_vertex_info.json
easysurfvis/data/ROI/FAN/L_rois.npy
easysurfvis/data/ROI/FAN/R_roi_values.npy
easysurfvis/data/ROI/FAN/R_roi_vertex_info.json
easysurfvis/data/ROI/FAN/R_rois.npy
easysurfvis/data/Sample/l_sampling_datas1.npy
easysurfvis/data/Sample/l_sampling_datas2.npy
easysurfvis/data/Sample/l_virtual_strip_mask.npy
easysurfvis/data/Sample/r_sampling_datas1.npy
easysurfvis/data/Sample/r_sampling_datas2.npy
easysurfvis/data/Sample/r_virtual_strip_mask.npy
easysurfvis/data/Sample/sample_3d_data.nii.gz
easysurfvis/data/Sulcus/L_sulcus.json
easysurfvis/data/Sulcus/L_sulcus_sensorimotor.json
easysurfvis/data/Sulcus/R_sulcus.json
easysurfvis/data/Sulcus/R_sulcus_sensorimotor.json
easysurfvis/data/Template/fs_LR.32k.L.flat.surf.gii
easysurfvis/data/Template/fs_LR.32k.L.inflated.surf.gii
easysurfvis/data/Template/fs_LR.32k.L.pial.surf.gii
easysurfvis/data/Template/fs_LR.32k.L.shape.gii
easysurfvis/data/Template/fs_LR.32k.L.white.surf.gii
easysurfvis/data/Template/fs_LR.32k.R.flat.surf.gii
easysurfvis/data/Template/fs_LR.32k.R.inflated.surf.gii
easysurfvis/data/Template/fs_LR.32k.R.pial.surf.gii
easysurfvis/data/Template/fs_LR.32k.R.shape.gii
easysurfvis/data/Template/fs_LR.32k.R.white.surf.gii
easysurfvis-1.0.2.dist-info/METADATA
easysurfvis-1.0.2.dist-info/WHEEL
easysurfvis-1.0.2.dist-info/top_level.txt
easysurfvis-1.0.2.dist-info/RECORD
