Metadata-Version: 2.4
Name: easysurfvis
Version: 1.0.2
Summary: visualize surface map easily
Home-page: https://github.com/SeojinYoon/easy_surf_vis
Author: seojin
Author-email: pures1@hanyang.ac.kr
Classifier: Programming Language :: Python :: 3
Classifier: License :: OSI Approved :: MIT License
Classifier: Operating System :: OS Independent
Requires-Python: <=3.12
Requires-Dist: SUITPy
Requires-Dist: neuroimagingtools
Requires-Dist: nibabel
Requires-Dist: nilearn
Requires-Dist: opencv-python
Requires-Dist: flask
Requires-Dist: flask-cors
Dynamic: author
Dynamic: author-email
Dynamic: classifier
Dynamic: description
Dynamic: description-content-type
Dynamic: home-page
Dynamic: requires-dist
Dynamic: requires-python
Dynamic: summary
